odoo10_addon_product_life_period-10.0.1.0.1-py3.6-nspkg.pth
odoo/addons/product_life_period/README.rst
odoo/addons/product_life_period/__init__.py
odoo/addons/product_life_period/__manifest__.py
odoo/addons/product_life_period/i18n/fr.po
odoo/addons/product_life_period/i18n/product_life_period.pot
odoo/addons/product_life_period/models/__init__.py
odoo/addons/product_life_period/models/product_life_period.py
odoo/addons/product_life_period/models/product_template.py
odoo/addons/product_life_period/security/ir.model.access.csv
odoo/addons/product_life_period/static/description/icon.png
odoo/addons/product_life_period/tests/__init__.py
odoo/addons/product_life_period/tests/test_product_life_period.py
odoo/addons/product_life_period/views/product_life_period_views.xml
odoo/addons/product_life_period/views/product_template.xml
odoo10_addon_product_life_period-10.0.1.0.1.dist-info/METADATA
odoo10_addon_product_life_period-10.0.1.0.1.dist-info/WHEEL
odoo10_addon_product_life_period-10.0.1.0.1.dist-info/namespace_packages.txt
odoo10_addon_product_life_period-10.0.1.0.1.dist-info/top_level.txt
odoo10_addon_product_life_period-10.0.1.0.1.dist-info/RECORD
